lolgram_inapp_bot/__init__.py
lolgram_inapp_bot/bot.py
lolgram_inapp_bot-0.1.0.dist-info/METADATA
lolgram_inapp_bot-0.1.0.dist-info/WHEEL
lolgram_inapp_bot-0.1.0.dist-info/top_level.txt
lolgram_inapp_bot-0.1.0.dist-info/RECORD
