Metadata-Version: 2.4
Name: lolgram-inapp-bot
Version: 0.1.0
Summary: A Python library for creating and managing in-apps in Lolgram
Home-page: https://github.com/yourusername/lolgram-inapp-bot
Author: Your Name
Author-email: your.email@example.com
Classifier: Programming Language :: Python :: 3
Classifier: License :: OSI Approved :: MIT License
Classifier: Operating System :: OS Independent
Requires-Python: >=3.6
Requires-Dist: requests>=2.25.1
Dynamic: author
Dynamic: author-email
Dynamic: classifier
Dynamic: description
Dynamic: description-content-type
Dynamic: home-page
Dynamic: requires-dist
Dynamic: requires-python
Dynamic: summary
